pubtools/pulplib/__init__.py
pubtools/pulplib/_impl/__init__.py
pubtools/pulplib/_impl/compat_attr.py
pubtools/pulplib/_impl/comps.py
pubtools/pulplib/_impl/criteria.py
pubtools/pulplib/_impl/hooks.py
pubtools/pulplib/_impl/log.py
pubtools/pulplib/_impl/page.py
pubtools/pulplib/_impl/util.py
pubtools/pulplib/_impl/client/__init__.py
pubtools/pulplib/_impl/client/client.py
pubtools/pulplib/_impl/client/copy.py
pubtools/pulplib/_impl/client/errors.py
pubtools/pulplib/_impl/client/poller.py
pubtools/pulplib/_impl/client/retry.py
pubtools/pulplib/_impl/client/search.py
pubtools/pulplib/_impl/client/ud_mappings.py
pubtools/pulplib/_impl/fake/__init__.py
pubtools/pulplib/_impl/fake/client.py
pubtools/pulplib/_impl/fake/controller.py
pubtools/pulplib/_impl/fake/match.py
pubtools/pulplib/_impl/fake/rpmlib.py
pubtools/pulplib/_impl/fake/state.py
pubtools/pulplib/_impl/fake/units.py
pubtools/pulplib/_impl/model/__init__.py
pubtools/pulplib/_impl/model/attr.py
pubtools/pulplib/_impl/model/common.py
pubtools/pulplib/_impl/model/convert.py
pubtools/pulplib/_impl/model/distributor.py
pubtools/pulplib/_impl/model/maintenance.py
pubtools/pulplib/_impl/model/task.py
pubtools/pulplib/_impl/model/validate.py
pubtools/pulplib/_impl/model/repository/__init__.py
pubtools/pulplib/_impl/model/repository/base.py
pubtools/pulplib/_impl/model/repository/container.py
pubtools/pulplib/_impl/model/repository/file.py
pubtools/pulplib/_impl/model/repository/repo_lock.py
pubtools/pulplib/_impl/model/repository/yum.py
pubtools/pulplib/_impl/model/unit/__init__.py
pubtools/pulplib/_impl/model/unit/base.py
pubtools/pulplib/_impl/model/unit/erratum.py
pubtools/pulplib/_impl/model/unit/file.py
pubtools/pulplib/_impl/model/unit/modulemd.py
pubtools/pulplib/_impl/model/unit/modulemd_defaults.py
pubtools/pulplib/_impl/model/unit/repo_metadata.py
pubtools/pulplib/_impl/model/unit/rpm.py
pubtools/pulplib/_impl/schema/__init__.py
pubtools/pulplib/_impl/schema/maintenance.yaml
pubtools_pulplib-2.43.2.dist-info/licenses/LICENSE
pubtools_pulplib-2.43.2.dist-info/METADATA
pubtools_pulplib-2.43.2.dist-info/WHEEL
pubtools_pulplib-2.43.2.dist-info/top_level.txt
pubtools_pulplib-2.43.2.dist-info/RECORD
