Metadata-Version: 2.4
Name: pubtools-pulplib
Version: 2.43.2
Summary: A Pulp library for publishing tools
Home-page: https://github.com/release-engineering/pubtools-pulplib
License: GNU General Public License
Project-URL: Documentation, https://release-engineering.github.io/pubtools-pulplib/
Project-URL: Changelog, https://github.com/release-engineering/pubtools-pulplib/blob/master/CHANGELOG.md
Classifier: Development Status :: 5 - Production/Stable
Classifier: Intended Audience :: Developers
Classifier: License :: OSI Approved :: GNU General Public License v3 or later (GPLv3+)
Classifier: Programming Language :: Python :: 3
Classifier: Topic :: Software Development :: Libraries :: Python Modules
Requires-Python: >=3.6
License-File: LICENSE
Requires-Dist: requests
Requires-Dist: more-executors>=2.8.1
Requires-Dist: PyYAML
Requires-Dist: jsonschema
Requires-Dist: attrs
Requires-Dist: frozenlist2
Requires-Dist: frozendict; python_version >= "3.6"
Requires-Dist: pubtools>=0.3.0
Requires-Dist: monotonic; python_version < "3.3"
Requires-Dist: defusedxml
Dynamic: classifier
Dynamic: description
Dynamic: description-content-type
Dynamic: home-page
Dynamic: license
Dynamic: license-file
Dynamic: project-url
Dynamic: requires-dist
Dynamic: requires-python
Dynamic: summary
